customers/__init__.py
customers/admin.py
customers/apps.py
customers/models.py
customers/serializers.py
customers/signals.py
customers/tests.py
customers/urls.py
customers/views.py
customers/migrations/0001_initial.py
customers/migrations/__init__.py
dj_auto_multitenant-0.0.6.dist-info/LICENSE
dj_auto_multitenant-0.0.6.dist-info/METADATA
dj_auto_multitenant-0.0.6.dist-info/WHEEL
dj_auto_multitenant-0.0.6.dist-info/top_level.txt
dj_auto_multitenant-0.0.6.dist-info/RECORD
